setup.py
ese/__init__.py
ese/ese.py
ese.egg-info/PKG-INFO
ese.egg-info/SOURCES.txt
ese.egg-info/dependency_links.txt
ese.egg-info/entry_points.txt
ese.egg-info/not-zip-safe
ese.egg-info/requires.txt
ese.egg-info/top_level.txt