Metadata-Version: 1.0
Name: ese
Version: 0.2
Summary: Tool to export Elasticsearch index from one cluster to another cluster
Home-page: https://github.com/merlin83/ese
Author: Khee Chin
Author-email: kheechin@gmail.com
License: MIT
Platform: UNKNOWN
